{
  "accesskeys": 1,
  "aria-allowed-attr": 3,
  "aria-required-attr": 2,
  "aria-required-children": 5,
  "aria-required-parent": 2,
  "aria-roles": 3,
  "aria-valid-attr-value": 2,
  "aria-valid-attr": 5,
  "audio-caption": 4,
  "button-name": 10,
  "bypass": 10,
  "color-contrast": 6,
  "definition-list": 1,
  "dlitem": 1,
  "document-title": 2,
  "duplicate-id": 5,
  "frame-title": 5,
  "html-has-lang": 4,
  "html-lang-valid": 1,
  "image-alt": 8,
  "input-image-alt": 1,
  "label": 10,
  "layout-table": 1,
  "link-name": 9,
  "list": 5,
  "listitem": 4,
  "meta-refresh": 1,
  "meta-viewport": 3,
  "object-alt": 4,
  "tabindex": 4,
  "td-headers-attr": 1,
  "th-has-data-cells": 1,
  "valid-lang": 1,
  "video-caption": 4,
  "video-description": 3,
  "custom-controls-labels": 0,
  "custom-controls-roles": 0,
  "interactive-element-affordance": 0,
  "logical-tab-order": 0,
  "offscreen-content-hidden": 0,
  "visual-order-follows-dom": 0,
  "heading-levels": 0,
  "managed-focus": 0
}
